<annotation>
	<folder>images</folder>
	<filename>image (66).jpg</filename>
	<path>C:\Users\lisan\Documents\Repositorios\Mecatronica Aplicada\mecatronica-aplicada\image_detection\barbijo\train\images\image (66).jpg</path>
	<source>
		<database>Unknown</database>
	</source>
	<size>
		<width>768</width>
		<height>1024</height>
		<depth>3</depth>
	</size>
	<segmented>0</segmented>
	<object>
		<name>barbijo</name>
		<pose>Unspecified</pose>
		<truncated>0</truncated>
		<difficult>0</difficult>
		<bndbox>
			<xmin>139</xmin>
			<ymin>298</ymin>
			<xmax>561</xmax>
			<ymax>635</ymax>
		</bndbox>
	</object>
</annotation>
